{
  "version": 2,
  "diagrams": {
    "theme-state-flow.mermaid": {
      "hash": "sha256:c0b40feeb6fa8d90",
      "generatedAt": "2026-04-16T14:37:59.235Z",
      "outputs": [
        {
          "file": "theme-state-flow-light.svg",
          "format": "svg",
          "theme": "light"
        },
        {
          "file": "theme-state-flow-dark.svg",
          "format": "svg",
          "theme": "dark"
        }
      ],
      "formats": ["svg"],
      "theme": "both",
      "mtimeMs": 1776318375569.9705,
      "size": 1194
    }
  }
}
